{
  "sources": [
    {
      "file": "morph/official-term-5.csv",
      "create": {
        "from": "morph",
        "scraper": "tmtmtmtm/kazakh-mazhilis",
        "query": "SELECT *, 5 AS term FROM data ORDER BY id"
      },
      "source": "http://www.parlam.kz",
      "generates": "membership"
    },
    {
      "file": "manual/terms.csv",
      "generates": "term"
    },
    {
      "file": "gender-balance/results.csv",
      "generates": "gender",
      "create": {
        "from": "gender-balance",
        "source": "Kazakhstan/Assembly"
      }
    },
    {
      "file": "morph/official.csv",
      "create": {
        "from": "morph",
        "scraper": "everypolitician-scrapers/kazakhstan-mazhilis",
        "query": "SELECT * FROM data ORDER BY id"
      },
      "source": "http://www.parlam.kz",
      "merge": {
          "incoming_field": "name",
          "existing_field": "name",
          "reconciliation_file": "reconciliation/official.csv"
      },
      "generates": "membership"
    },
    {
      "file": "wikidata/groups.json",
      "generates": "group",
      "create": {
        "from": "group-wikidata",
        "source": "manual/group_wikidata.csv"
      }
    },
    {
      "file": "wikidata/elections.json",
      "generates": "wikidata-elections",
      "create": {
        "from": "election-wikidata",
        "base": "Q22333025"
      }
    }
  ]
}
